nunavut/__init__.py
nunavut/__main__.py
nunavut/_dependencies.py
nunavut/_exceptions.py
nunavut/_generators.py
nunavut/_namespace.py
nunavut/_postprocessors.py
nunavut/_templates.py
nunavut/_utilities.py
nunavut/_version.py
nunavut/cli/__init__.py
nunavut/cli/runners.py
nunavut/jinja/__init__.py
nunavut/jinja/environment.py
nunavut/jinja/extensions.py
nunavut/jinja/loaders.py
nunavut/jinja/jinja2/__init__.py
nunavut/jinja/jinja2/_compat.py
nunavut/jinja/jinja2/_identifier.py
nunavut/jinja/jinja2/asyncfilters.py
nunavut/jinja/jinja2/asyncsupport.py
nunavut/jinja/jinja2/bccache.py
nunavut/jinja/jinja2/compiler.py
nunavut/jinja/jinja2/constants.py
nunavut/jinja/jinja2/debug.py
nunavut/jinja/jinja2/defaults.py
nunavut/jinja/jinja2/environment.py
nunavut/jinja/jinja2/exceptions.py
nunavut/jinja/jinja2/ext.py
nunavut/jinja/jinja2/filters.py
nunavut/jinja/jinja2/idtracking.py
nunavut/jinja/jinja2/lexer.py
nunavut/jinja/jinja2/loaders.py
nunavut/jinja/jinja2/meta.py
nunavut/jinja/jinja2/nativetypes.py
nunavut/jinja/jinja2/nodes.py
nunavut/jinja/jinja2/optimizer.py
nunavut/jinja/jinja2/parser.py
nunavut/jinja/jinja2/runtime.py
nunavut/jinja/jinja2/sandbox.py
nunavut/jinja/jinja2/tests.py
nunavut/jinja/jinja2/utils.py
nunavut/jinja/jinja2/visitor.py
nunavut/jinja/markupsafe/__init__.py
nunavut/jinja/markupsafe/_compat.py
nunavut/jinja/markupsafe/_constants.py
nunavut/jinja/markupsafe/_native.py
nunavut/lang/__init__.py
nunavut/lang/_common.py
nunavut/lang/_config.py
nunavut/lang/_language.py
nunavut/lang/properties.yaml
nunavut/lang/c/__init__.py
nunavut/lang/c/support/__init__.py
nunavut/lang/c/support/serialization.j2
nunavut/lang/c/templates/DelimitedType.j2
nunavut/lang/c/templates/ServiceType.j2
nunavut/lang/c/templates/StructureType.j2
nunavut/lang/c/templates/UnionType.j2
nunavut/lang/c/templates/__init__.py
nunavut/lang/c/templates/base.j2
nunavut/lang/c/templates/definitions.j2
nunavut/lang/c/templates/deserialization.j2
nunavut/lang/c/templates/serialization.j2
nunavut-2.3.1.dist-info/LICENSE.rst
nunavut-2.3.1.dist-info/METADATA
nunavut-2.3.1.dist-info/WHEEL
nunavut-2.3.1.dist-info/entry_points.txt
nunavut-2.3.1.dist-info/top_level.txt
nunavut-2.3.1.dist-info/RECORD
