Metadata-Version: 2.1
Name: nunavut
Version: 2.3.1
Summary: Generate code from DSDL using Jinja2 templates.
Home-page: https://opencyphal.org
Author: OpenCyphal Development Team
Author-email: maintainers@opencyphal.org
License: MIT
Keywords: uavcan,dsdl,can,can-bus,codegen,cyphal,opencyphal
Classifier: Development Status :: 3 - Alpha
Classifier: Environment :: Console
Classifier: Intended Audience :: Developers
Classifier: License :: OSI Approved :: MIT License
Classifier: Programming Language :: Python
Classifier: Programming Language :: Python :: 3
Classifier: Programming Language :: Python :: 3.7
Classifier: Programming Language :: Python :: 3.8
Classifier: Programming Language :: Python :: 3.9
Classifier: Programming Language :: Python :: 3.10
Classifier: Programming Language :: Python :: 3.11
Classifier: Programming Language :: Python :: 3 :: Only
Classifier: Topic :: Scientific/Engineering
Classifier: Topic :: Software Development :: Embedded Systems
Classifier: Topic :: Software Development :: Libraries
Classifier: Topic :: Software Development :: Code Generators
Classifier: Topic :: Software Development :: Build Tools
Classifier: Topic :: System :: Distributed Computing
Classifier: Topic :: System :: Networking
Classifier: Typing :: Typed
Requires-Python: >=3.7
License-File: LICENSE.rst
